<?xml version="1.0" encoding="UTF-8" ?>
<!DOCTYPE struts PUBLIC
    "-//Apache Software Foundation//DTD Struts Configuration 2.1//EN"
    "http://struts.apache.org/dtds/struts-2.1.dtd">
<struts>

	<package name="NetworkCode" extends="struts-default">
		<!-- action标签描述的是struts的控制器，name是对应的路径，class是action的类名 -->
		<action name="Code!*" class="com.network.www.action.CodeAction">
			<result>/info/code.jsp</result>
			<!-- input：指定action校验出现错误时会转到的页面 -->
			<result name="input">/info/loginerror.jsp</result>
			<result name="already">/info/loginerror.jsp</result>
		</action>
	</package>

</struts>